setup.cfg
setup.py
dio/Action.py
dio/Api.py
dio/Backup.py
dio/Domain.py
dio/Droplet.py
dio/Image.py
dio/Kernel.py
dio/Manager.py
dio/Network.py
dio/Records.py
dio/Region.py
dio/SSHKey.py
dio/Size.py
dio/Snapshot.py
dio/__init__.py
dio.egg-info/PKG-INFO
dio.egg-info/SOURCES.txt
dio.egg-info/dependency_links.txt
dio.egg-info/requires.txt
dio.egg-info/top_level.txt