Metadata-Version: 1.1
Name: dio
Version: 0.3.10
Summary: Python API for DigitalOcean v2.0 REST API
Home-page: http://corndogcomputers.github.io/python-dio
Author: Rob Johnson
Author-email: info@corndogcomputers.com
License: The MIT License (MIT)
